tango_mlflow/__init__.py
tango_mlflow/__main__.py
tango_mlflow/commands/__init__.py
tango_mlflow/commands/subcommand.py
tango_mlflow/commands/tune.py
tango_mlflow/flax_train_callback.py
tango_mlflow/format.py
tango_mlflow/py.typed
tango_mlflow/step.py
tango_mlflow/step_cache.py
tango_mlflow/torch_train_callback.py
tango_mlflow/util.py
tango_mlflow/workspace.py
tango_mlflow-2.0.0.dist-info/LICENSE
tango_mlflow-2.0.0.dist-info/METADATA
tango_mlflow-2.0.0.dist-info/WHEEL
tango_mlflow-2.0.0.dist-info/entry_points.txt
tango_mlflow-2.0.0.dist-info/RECORD
